PyPk_Client/__main__.py
PyPk_Client-0.0.0.dist-info/METADATA
PyPk_Client-0.0.0.dist-info/WHEEL
PyPk_Client-0.0.0.dist-info/top_level.txt
PyPk_Client-0.0.0.dist-info/RECORD
