Metadata-Version: 2.1
Name: PyPk_Client
Version: 0.0.0
Summary: NOTICE:You'l need the the PyPK_Server Module To use this
Requires-Dist: flask-socketio
Requires-Dist: ttkbootstrap
Requires-Dist: websocket
